LICENSE
MANIFEST.in
README.md
setup.py
evgraf/__init__.py
evgraf/crystal_comparator.py
evgraf/crystal_reducer.py
evgraf/crystal_reduction.py
evgraf/inversion_symmetry.py
evgraf/subgroup_enumeration.py
evgraf.egg-info/PKG-INFO
evgraf.egg-info/SOURCES.txt
evgraf.egg-info/dependency_links.txt
evgraf.egg-info/requires.txt
evgraf.egg-info/top_level.txt
evgraf/utils/__init__.py
evgraf/utils/axis_permutation.py
evgraf/utils/minkowski_reduction.py
evgraf/utils/pbc.py
evgraf/utils/rotation_matrix.py
evgraf/utils/standardization.py
src/crystalline.cpp
src/crystalline.h
src/evgrafcpp_module.cpp
src/lup_decomposition.cpp
src/lup_decomposition.h
src/matrix_vector.cpp
src/matrix_vector.h
src/rectangular_lsap.cpp
src/rectangular_lsap.h
src/wrap_positions.cpp
src/wrap_positions.h