Metadata-Version: 1.2
Name: evgraf
Version: 0.1.6
Summary: Geometric analysis of crystal structures
Home-page: https://github.com/pmla/evgraf
Author: P. M. Larsen
Author-email: pmla@fysik.dtu.dk
License: UNKNOWN
Platform: UNKNOWN
Requires-Python: >=3.5.0
